.pre-commit-config.yaml
CHANGES.rst
CONTRIBUTORS.rst
DEVELOP.rst
LICENSE.GPL
LICENSE.rst
MANIFEST.in
README.rst
setup.cfg
setup.py
docs/conf.py
docs/index.rst
src/collective/__init__.py
src/collective.pintarito.egg-info/PKG-INFO
src/collective.pintarito.egg-info/SOURCES.txt
src/collective.pintarito.egg-info/dependency_links.txt
src/collective.pintarito.egg-info/entry_points.txt
src/collective.pintarito.egg-info/namespace_packages.txt
src/collective.pintarito.egg-info/not-zip-safe
src/collective.pintarito.egg-info/requires.txt
src/collective.pintarito.egg-info/top_level.txt
src/collective/pintarito/__init__.py
src/collective/pintarito/configure.zcml
src/collective/pintarito/interfaces.py
src/collective/pintarito/permissions.zcml
src/collective/pintarito/setuphandlers.py
src/collective/pintarito/testing.py
src/collective/pintarito/browser/__init__.py
src/collective/pintarito/browser/configure.zcml
src/collective/pintarito/browser/selection.py
src/collective/pintarito/browser/overrides/.gitkeep
src/collective/pintarito/browser/overrides/plone.app.layout.viewlets.logo.pt
src/collective/pintarito/browser/static/.gitkeep
src/collective/pintarito/browser/static/blue.css
src/collective/pintarito/browser/static/brownish.css
src/collective/pintarito/browser/static/fancy-pastels.css
src/collective/pintarito/browser/static/green.css
src/collective/pintarito/browser/static/orange.css
src/collective/pintarito/browser/static/pintarito_base.css
src/collective/pintarito/browser/static/purple.css
src/collective/pintarito/browser/static/red.css
src/collective/pintarito/browser/static/yellow.css
src/collective/pintarito/browser/templates/styles.pt
src/collective/pintarito/controlpanel/__init__.py
src/collective/pintarito/controlpanel/configure.zcml
src/collective/pintarito/controlpanel/settings.py
src/collective/pintarito/locales/README.rst
src/collective/pintarito/locales/__init__.py
src/collective/pintarito/locales/collective.pintarito.pot
src/collective/pintarito/locales/update.py
src/collective/pintarito/locales/update.sh
src/collective/pintarito/locales/en/LC_MESSAGES/collective.pintarito.po
src/collective/pintarito/locales/it/LC_MESSAGES/collective.pintarito.po
src/collective/pintarito/profiles/default/browserlayer.xml
src/collective/pintarito/profiles/default/controlpanel.xml
src/collective/pintarito/profiles/default/metadata.xml
