Metadata-Version: 2.1
Name: collective.pintarito
Version: 0.0.1
Summary: An add-on for Plone
Home-page: https://github.com/collective/collective.pintarito
Author: ale-rt
Author-email: alessandro.pisa@gmail.com
License: GPL version 2
Project-URL: PyPI, https://pypi.python.org/pypi/collective.pintarito
Project-URL: Source, https://github.com/collective/collective.pintarito
Project-URL: Tracker, https://github.com/collective/collective.pintarito/issues
Keywords: Python Plone CMS
Classifier: Environment :: Web Environment
Classifier: Framework :: Plone
Classifier: Framework :: Plone :: Addon
Classifier: Framework :: Plone :: 6.0
Classifier: Programming Language :: Python
Classifier: Programming Language :: Python :: 3.8
Classifier: Programming Language :: Python :: 3.9
Classifier: Programming Language :: Python :: 3.10
Classifier: Programming Language :: Python :: 3.11
Classifier: Operating System :: OS Independent
Classifier: License :: OSI Approved :: GNU General Public License v2 (GPLv2)
Requires-Python: >=3.7
Provides-Extra: test
License-File: LICENSE.GPL
License-File: LICENSE.rst
